democritus_regexes
tests
