Metadata-Version: 2.1
Name: democritus-regexes
Version: 2021.2.1
Summary: Democritus functions for working with regexes in Python.
Home-page: https://github.com/democritus/democritus-regexes
Author: Floyd Hightower
Author-email: floyd.hightower27@gmail.com
License: MIT license
Keywords: regexes,regex,regular expression,democritus,regex utility,regex utils,re utils
Platform: UNKNOWN
Classifier: Development Status :: 2 - Pre-Alpha
Classifier: Intended Audience :: Developers
Classifier: License :: OSI Approved :: MIT License
Classifier: Natural Language :: English
Classifier: Programming Language :: Python :: 3
Classifier: Programming Language :: Python :: 3.4
Classifier: Programming Language :: Python :: 3.5
Classifier: Programming Language :: Python :: 3.6
Classifier: Programming Language :: Python :: 3.7
Classifier: Programming Language :: Python :: 3.8
Classifier: Programming Language :: Python :: 3.9
